testversioningpkg/__init__.py
testversioningpkg/customs/event_a/__init__.py
testversioningpkg/customs/event_a/agenda.py
testversioningpkg/customs/event_b/__init__.py
testversioningpkg/customs/event_b/agenda.py
testversioningpkg/main.py
testversioningpkg/versions/__init__.py
testversioningpkg/versions/v1/__init__.py
testversioningpkg/versions/v1/agenda.py
testversioningpkg/versions/v2/__init__.py
testversioningpkg/versions/v2/agenda.py
testversioningpkg/versions/v3/__init__.py
testversioningpkg/versions/v3/floorplan.py
testversioningpkg/versions/v4/__init__.py
testversioningpkg/versions/v4/floorplan.py
testversioningpkg-0.1.3.dist-info/WHEEL
testversioningpkg-0.1.3.dist-info/METADATA
testversioningpkg-0.1.3.dist-info/RECORD
