Metadata-Version: 2.1
Name: testversioningpkg
Version: 0.1.3
Summary: Test versioning package
Author: Marchandev
Author-email: dhiva.hanifsyah@gmail.com
Requires-Python: >=3.9,<4.0
Classifier: Programming Language :: Python :: 3
Classifier: Programming Language :: Python :: 3.10
Classifier: Programming Language :: Python :: 3.9
